[{
    "title": "City. Coast. Country. The City of Wyndham selects riskcloud.NET",
    "body": "<p>Melbourne – PAN Software, developer of multi-award winning Enterprise Risk Intelligence Software (ERIS) – is pleased announced that the City of Wyndham has selected riskcloud.NET.</p>",
    "id": 1
}, {
    "title": "riskcloud.NET BCM Module on show @ the 2014 Business Continuity Summit",
    "body": "<p>Sydney – PAN Software, developer of multi-award winning Enterprise Risk Intelligence Software (ERIS) is excited to announce that we are again a proud sponsor of the 2014 Business Continuity Summit.</p>",
    "id": 2
}]